{
  "date": "Sep 26, 2025",
  "country": "France",
  "marketCode": "fr-FR",
  "title": "Espèce de rongeur…. toi-même !",
  "bsTitle": "",
  "caption": "",
  "copyright": "Tamia mineur, forêt nationale de Kootenai, Montana, États-Unis (© Donald M. Jones/Minden Pictures)",
  "copyrightOnly": "",
  "copyrightLink": "/search?q=Tamia+mineur&form=hpcapt&filters=HpDate%3a%2220250925_2200%22",
  "description": "Tamia mineur, forêt nationale de Kootenai, Montana, États-Unis",
  "quiz": "/search?q=Bing+homepage+quiz&filters=WQOskey:%22HPQuiz_20250925_AutumnChipmunk%22&FORM=HPQUIZ",
  "hash": "7309fb6f1e2fe4de121e82c09f0d853a",
  "imageResolutions": [
    {
      "resolution": "Standard",
      "url": "https://www.bing.com/th?id=OHR.AutumnChipmunk_FR-FR1635534631_1366x768.jpg",
      "size": "1366x768"
    },
    {
      "resolution": "FullHD",
      "url": "https://www.bing.com/th?id=OHR.AutumnChipmunk_FR-FR1635534631_1920x1080.jpg",
      "size": "1920x1080"
    },
    {
      "resolution": "HD",
      "url": "https://www.bing.com/th?id=OHR.AutumnChipmunk_FR-FR1635534631_1920x1200.jpg",
      "size": "1920x1200"
    },
    {
      "resolution": "UHD4K",
      "url": "https://www.bing.com/th?id=OHR.AutumnChipmunk_FR-FR1635534631_UHD.jpg",
      "size": "3840x2160"
    }
  ],
  "timeInfo": {
    "startDate": "20250925",
    "endDate": "20250926",
    "fullStartDateTime": "202509252200"
  },
  "createdAt": "202509260000",
  "originalUrlBase": "/th?id=OHR.AutumnChipmunk_FR-FR1635534631"
}