{
  "date": "2025-09-25",
  "country": "France",
  "marketCode": "fr-FR",
  "title": "La raison du plus fort est Chittorgarh !",
  "copyright": "Fort de Chittorgarh, Rajasthan, Inde (© chetansoni/Shutterstock)",
  "copyrightLink": "https://www.bing.com/search?q=Fort+de+Chittorgarh+Inde&form=hpcapt&filters=HpDate%3a%2220250924_2200%22",
  "description": "Fort de Chittorgarh, Rajasthan, Inde",
  "quiz": "/search?q=Bing+homepage+quiz&filters=WQOskey:%22HPQuiz_20250924_FortChittorgarh%22&FORM=HPQUIZ",
  "hash": "f255e51d54367aeab7e392470dddc7dd",
  "imageResolutions": [
    {
      "resolution": "UHD",
      "url": "https://www.bing.com/th?id=OHR.FortChittorgarh_FR-FR5443907474_UHD.jpg",
      "size": "Ultra High Definition (~4K)"
    },
    {
      "resolution": "HD",
      "url": "https://www.bing.com/th?id=OHR.FortChittorgarh_FR-FR5443907474_1920x1200.jpg",
      "size": "1920x1200"
    },
    {
      "resolution": "Full HD",
      "url": "https://www.bing.com/th?id=OHR.FortChittorgarh_FR-FR5443907474_1920x1080.jpg",
      "size": "1920x1080"
    },
    {
      "resolution": "Standard",
      "url": "https://www.bing.com/th?id=OHR.FortChittorgarh_FR-FR5443907474_1366x768.jpg",
      "size": "1366x768"
    }
  ],
  "timeInfo": {
    "StartDate": "2025-09-24",
    "EndDate": "2025-09-25",
    "FullStartDateTime": "2025-09-24T22:00:00Z",
    "OriginalTimeFields": {
      "startDate": "20250924",
      "fullStartDate": "202509242200",
      "endDate": "20250925"
    }
  },
  "createdAt": "2025-09-25T02:11:01.4258829+00:00",
  "originalUrlBase": "/th?id=OHR.FortChittorgarh_FR-FR5443907474"
}