{
  "date": "2. Okt.. 2025",
  "country": "Germany",
  "marketCode": "de-DE",
  "title": "Die Natur in ihrer reinsten Form",
  "bsTitle": "Die Natur in ihrer reinsten Form",
  "caption": "Oxbow Bend am Snake River, Grand-Teton-Nationalpark, Wyoming, USA",
  "copyright": "Oxbow Bend am Snake River, Grand-Teton-Nationalpark, Wyoming, USA (© DanitaDelimont.com/AWL Images/SuperStock)",
  "copyrightOnly": "© DanitaDelimont.com/AWL Images/SuperStock",
  "copyrightLink": "/search?q=Grand-Teton-Nationalpark+Wyoming+USA&form=hpcapt&filters=HpDate%3a%2220251001_2200%22",
  "description": "Auf dem heutigen Bild sieht man das majestätische Oxbow Bend am Snake River im Grand-Teton-Nationalpark in Wyoming, USA. Diese ikonische Flussschleife bietet eine der meistfotografierten Aussichten des Parks, besonders bei Sonnenaufgang, wenn sich die Gipfel der Teton Range im ruhigen Wasser spiegeln. Der Ort ist bekannt für seine Stille, seine Artenvielfalt und als Lebensraum für Elche, Weißkopfseeadler und Fischotter. Im Herbst färben die Espen das Landschaftsbild in ein leuchtendes Gold und schaffen ein unvergessliches Naturschauspiel. Oxbow Bend ist nicht nur ein Hotspot für Fotografen, sondern auch ein Symbol für das harmonische Zusammenspiel von Wasser, Bergen und Himmel.",
  "quiz": "/search?q=Bing+homepage+quiz&filters=WQOskey:%22HPQuiz_20251001_OxbowBend%22&FORM=HPQUIZ",
  "hash": "2eed728a0e2761a356f35bc1166b0481",
  "imageResolutions": [
    {
      "resolution": "Standard",
      "url": "https://www.bing.com/th?id=OHR.OxbowBend_DE-DE1318690148_1366x768.jpg",
      "size": "1366x768"
    },
    {
      "resolution": "FullHD",
      "url": "https://www.bing.com/th?id=OHR.OxbowBend_DE-DE1318690148_1920x1080.jpg",
      "size": "1920x1080"
    },
    {
      "resolution": "HD",
      "url": "https://www.bing.com/th?id=OHR.OxbowBend_DE-DE1318690148_1920x1200.jpg",
      "size": "1920x1200"
    },
    {
      "resolution": "UHD4K",
      "url": "https://www.bing.com/th?id=OHR.OxbowBend_DE-DE1318690148_UHD.jpg",
      "size": "3840x2160"
    }
  ],
  "timeInfo": {
    "startDate": "20251001",
    "endDate": "20251002",
    "fullStartDateTime": "202510012200",
    "originalTimeFields": {
      "startDate": "20251001",
      "fullStartDate": "202510012200",
      "endDate": "20251002"
    }
  },
  "createdAt": "202510020000",
  "originalUrlBase": "/th?id=OHR.OxbowBend_DE-DE1318690148"
}
