{
  "date": "Oct 04, 2025",
  "country": "Italy",
  "marketCode": "it-IT",
  "title": "Missione: Possibile",
  "bsTitle": "",
  "caption": "",
  "copyright": "Pannelli solari della ISS visti dalla SpaceX Crew Dragon Endeavour (© NASA)",
  "copyrightOnly": "",
  "copyrightLink": "/search?q=Settimana+mondiale+dello+Spazio&form=hpcapt",
  "description": "",
  "quiz": "/search?q=Bing+homepage+quiz&filters=WQOskey:%22HPQuiz_20251003_DragonEndeavour%22&FORM=HPQUIZ",
  "hash": "6b61b53c689ff847b419d06375532ae5",
  "imageResolutions": [
    {
      "resolution": "Standard",
      "url": "https://www.bing.com/th?id=OHR.DragonEndeavour_IT-IT7184624651_1366x768.jpg",
      "size": "1366x768"
    },
    {
      "resolution": "FullHD",
      "url": "https://www.bing.com/th?id=OHR.DragonEndeavour_IT-IT7184624651_1920x1080.jpg",
      "size": "1920x1080"
    },
    {
      "resolution": "HD",
      "url": "https://www.bing.com/th?id=OHR.DragonEndeavour_IT-IT7184624651_1920x1200.jpg",
      "size": "1920x1200"
    },
    {
      "resolution": "UHD4K",
      "url": "https://www.bing.com/th?id=OHR.DragonEndeavour_IT-IT7184624651_UHD.jpg",
      "size": "3840x2160"
    }
  ],
  "timeInfo": {
    "startDate": "20251003",
    "endDate": "20251004",
    "fullStartDateTime": "202510032200",
    "originalTimeFields": {
      "startDate": "20251003",
      "fullStartDate": "202510032200",
      "endDate": "20251004"
    }
  },
  "createdAt": "202510040000",
  "originalUrlBase": "/th?id=OHR.DragonEndeavour_IT-IT7184624651"
}
